derived_attributes/__init__.py
derived_attributes/derive.py
derived_attributes/verbs.py
examples/__init__.py
examples/derive_attributes_customer_promos.py
examples/derive_rules_fraud_detection.py
examples/derive_triggers_system_monitoring.py
src/__init__.py
src/derived_attributes/__init__.py
src/derived_attributes/derive.py
src/derived_attributes/verbs.py
tests/__init__.py
tests/tests.py
derived_attributes-0.3.1.dist-info/LICENSE
derived_attributes-0.3.1.dist-info/METADATA
derived_attributes-0.3.1.dist-info/WHEEL
derived_attributes-0.3.1.dist-info/top_level.txt
derived_attributes-0.3.1.dist-info/RECORD
