Metadata-Version: 2.1
Name: derived-attributes
Version: 0.3.1
Summary: A Python library for applying computations to a JSON object using a Subject-Verb-Object grammar.
Home-page: https://github.com/shaungallagher/derived-attributes
Author: Shaun Gallagher
Author-email: github-shaun@pressbin.com
License: UNKNOWN
Platform: UNKNOWN
Classifier: Programming Language :: Python :: 3
Classifier: License :: OSI Approved :: MIT License
Classifier: Operating System :: OS Independent
Requires-Python: >=3.7
License-File: LICENSE
Requires-Dist: jsonata-python (>=0.3.0)
Requires-Dist: jsonpath-ng (>=1.5.3)
